deepsensor/__init__.py
deepsensor/config.py
deepsensor/errors.py
deepsensor/plot.py
deepsensor/py.typed
deepsensor/active_learning/__init__.py
deepsensor/active_learning/acquisition_fns.py
deepsensor/active_learning/algorithms.py
deepsensor/data/__init__.py
deepsensor/data/loader.py
deepsensor/data/processor.py
deepsensor/data/sources.py
deepsensor/data/task.py
deepsensor/data/utils.py
deepsensor/eval/__init__.py
deepsensor/eval/metrics.py
deepsensor/model/__init__.py
deepsensor/model/convnp.py
deepsensor/model/defaults.py
deepsensor/model/model.py
deepsensor/model/nps.py
deepsensor/model/pred.py
deepsensor/tensorflow/__init__.py
deepsensor/torch/__init__.py
deepsensor/train/__init__.py
deepsensor/train/train.py
tests/__init__.py
tests/test_active_learning.py
tests/test_data_processor.py
tests/test_model.py
tests/test_plotting.py
tests/test_task.py
tests/test_task_loader.py
tests/test_training.py
tests/utils.py
deepsensor-0.4.2.dist-info/METADATA
deepsensor-0.4.2.dist-info/WHEEL
deepsensor-0.4.2.dist-info/top_level.txt
deepsensor-0.4.2.dist-info/RECORD
