Metadata-Version: 2.1
Name: deepsensor
Version: 0.4.2
Summary: A Python package for modelling xarray and pandas data with neural processes.
Home-page: https://github.com/alan-turing-institute/deepsensor
Author: Tom R. Andersson
Author-email: tomandersson3@gmail.com
License: MIT
Platform: unix
Platform: linux
Platform: osx
Requires-Python: >=3.8
Requires-Dist: neuralprocesses
Requires-Dist: backends-matrix
Requires-Dist: backends
Requires-Dist: numpy
Requires-Dist: pandas
Requires-Dist: xarray
Requires-Dist: dask
Requires-Dist: distributed
Requires-Dist: pyshp
Requires-Dist: tqdm
Requires-Dist: seaborn
Requires-Dist: pooch
Requires-Dist: gcsfs
Requires-Dist: zarr
Provides-Extra: testing
Requires-Dist: pytest; extra == "testing"
Requires-Dist: pytest-cov; extra == "testing"
Requires-Dist: mypy; extra == "testing"
Requires-Dist: tox; extra == "testing"
